<?xml version="1.0" encoding="UTF-8" standalone="yes"?>
<RaiseFault async="false" continueOnError="false" enabled="true" name="RaiseFault.404PageNotFound">
    <DisplayName>RaiseFault.404PageNotFound</DisplayName>
    <Properties/>
    <FaultResponse>
        <Set>
            <Headers/>
            <Payload contentType="text/plain"/>
            <StatusCode>404</StatusCode>
            <ReasonPhrase>Not Found</ReasonPhrase>
        </Set>
        <AssignVariable>
            <Name>bref.error.code</Name>
            <Value>value</Value>
        </AssignVariable>
        <AssignVariable>
            <Name>bref.error.coding.code</Name>
            <Value>PROXY_FORBIDDEN</Value>
        </AssignVariable>
        <AssignVariable>
            <Name>bref.error.diagnostics</Name>
            <Value>The resource was not found within BaRS: (further diagnostics information, error message/error text)</Value>
        </AssignVariable>
    </FaultResponse>
    <IgnoreUnresolvedVariables>true</IgnoreUnresolvedVariables>
</RaiseFault>